pyvfp/__init__.py
pyvfp/foxpro.py
pyvfp/bin/__init__.py
pyvfp/bin/vfp.exe
pyvfp-0.1.2.dist-info/METADATA
pyvfp-0.1.2.dist-info/WHEEL
pyvfp-0.1.2.dist-info/top_level.txt
pyvfp-0.1.2.dist-info/RECORD
