Metadata-Version: 2.1
Name: pyvfp
Version: 0.1.2
Requires-Dist: pandas (~=2.0.3)
Requires-Dist: setuptools (~=68.0.0)
